{
  "positions_top20": [
    {
      "id": "FIX_2026-05-20",
      "ticker": "FIX",
      "sector": "Industrials",
      "entry_date": "2026-05-20",
      "entry_price": 1872.5,
      "entry_rsi2": 3.1767659900552445,
      "entry_rsi30": 58.868260152653136,
      "entry_rs_vs_spy": 5.3394314786773265,
      "entry_volume_ratio": 0.06473959692697623,
      "entry_score": 14.309597483201719,
      "current_price": 1849.7850341796875,
      "current_pnl_pct": -1.213082286799061,
      "current_pnl_dollars": -60.65411433995305,
      "hold_days": 0,
      "status": "open",
      "exit_signal": null,
      "position_size": 5000,
      "in_top20": true
    },
    {
      "id": "STX_2026-05-20",
      "ticker": "STX",
      "sector": "Information Technology",
      "entry_date": "2026-05-20",
      "entry_price": 753.0,
      "entry_rsi2": 3.77422034992,
      "entry_rsi30": 65.45743153503098,
      "entry_rs_vs_spy": 26.568503042343306,
      "entry_volume_ratio": 0.04254156990226344,
      "entry_score": 27.664267149671318,
      "current_price": 744.1699829101562,
      "current_pnl_pct": -1.17264503185176,
      "current_pnl_dollars": -58.632251592588005,
      "hold_days": 0,
      "status": "open",
      "exit_signal": null,
      "position_size": 5000,
      "in_top20": true
    },
    {
      "id": "NVT_2026-05-20",
      "ticker": "NVT",
      "sector": "Electrical Components & Equipment",
      "entry_date": "2026-05-20",
      "entry_price": 160.1699981689453,
      "entry_rsi2": 4.38057920549052,
      "entry_rsi30": 60.33749404758043,
      "entry_rs_vs_spy": 11.183436666113211,
      "entry_volume_ratio": 0.02364356561214219,
      "entry_score": 17.54049608319288,
      "current_price": 160.86000061035156,
      "current_pnl_pct": 0.43079381238328995,
      "current_pnl_dollars": 21.539690619164496,
      "hold_days": 0,
      "status": "open",
      "exit_signal": null,
      "position_size": 5000,
      "in_top20": true
    },
    {
      "id": "VMI_2026-05-20",
      "ticker": "VMI",
      "sector": "Industrial Machinery & Supplies & Components",
      "entry_date": "2026-05-20",
      "entry_price": 494.1300048828125,
      "entry_rsi2": 2.3725370626759457,
      "entry_rsi30": 57.21750808605591,
      "entry_rs_vs_spy": 2.5801478766408037,
      "entry_volume_ratio": 0.02019283935488425,
      "entry_score": 12.936037948063333,
      "current_price": 497.3900146484375,
      "current_pnl_pct": 0.6597473809343279,
      "current_pnl_dollars": 32.987369046716395,
      "hold_days": 0,
      "status": "open",
      "exit_signal": null,
      "position_size": 5000,
      "in_top20": true
    },
    {
      "id": "ROG_2026-05-20",
      "ticker": "ROG",
      "sector": "Electronic Components",
      "entry_date": "2026-05-20",
      "entry_price": 131.3699951171875,
      "entry_rsi2": 4.584553971529488,
      "entry_rsi30": 57.075794528542026,
      "entry_rs_vs_spy": 5.536113939691333,
      "entry_volume_ratio": 0.017007323794128396,
      "entry_score": 11.452042615603,
      "current_price": 131.0,
      "current_pnl_pct": -0.28164354947067816,
      "current_pnl_dollars": -14.082177473533907,
      "hold_days": 0,
      "status": "open",
      "exit_signal": null,
      "position_size": 5000,
      "in_top20": true
    },
    {
      "id": "VECO_2026-05-20",
      "ticker": "VECO",
      "sector": "Semiconductor Materials & Equipment",
      "entry_date": "2026-05-20",
      "entry_price": 56.31999969482422,
      "entry_rsi2": 2.526389671611369,
      "entry_rsi30": 62.73940224539524,
      "entry_rs_vs_spy": 8.526640112809947,
      "entry_volume_ratio": 0.04136459924707302,
      "entry_score": 18.68068376582257,
      "current_price": 57.025001525878906,
      "current_pnl_pct": 1.2517788261271479,
      "current_pnl_dollars": 62.58894130635739,
      "hold_days": 0,
      "status": "open",
      "exit_signal": null,
      "position_size": 5000,
      "in_top20": true
    },
    {
      "id": "MCHP_2026-05-20",
      "ticker": "MCHP",
      "sector": "Information Technology",
      "entry_date": "2026-05-20",
      "entry_price": 93.63999938964844,
      "entry_rsi2": 2.207752640766145,
      "entry_rsi30": 61.09111629729192,
      "entry_rs_vs_spy": 9.837552070029698,
      "entry_volume_ratio": 0.08175834086652578,
      "entry_score": 20.830838492830036,
      "current_price": 93.63999938964844,
      "current_pnl_pct": 0.0,
      "current_pnl_dollars": 0.0,
      "hold_days": 0,
      "status": "open",
      "exit_signal": null,
      "position_size": 5000,
      "in_top20": true
    },
    {
      "id": "FLEX_2026-05-20",
      "ticker": "FLEX",
      "sector": "Electronic Manufacturing Services",
      "entry_date": "2026-05-20",
      "entry_price": 133.3300018310547,
      "entry_rsi2": 4.727103490863556,
      "entry_rsi30": 68.63992658788753,
      "entry_rs_vs_spy": 52.39457737333362,
      "entry_volume_ratio": 0.24015597985175982,
      "entry_score": 26.746572917531687,
      "current_price": 133.3300018310547,
      "current_pnl_pct": 0.0,
      "current_pnl_dollars": 0.0,
      "hold_days": 0,
      "status": "open",
      "exit_signal": null,
      "position_size": 5000,
      "in_top20": true
    },
    {
      "id": "MSM_2026-05-20",
      "ticker": "MSM",
      "sector": "Trading Companies & Distributors",
      "entry_date": "2026-05-20",
      "entry_price": 104.77999877929688,
      "entry_rsi2": 4.247260626263056,
      "entry_rsi30": 60.495020372311046,
      "entry_rs_vs_spy": 4.69637124363631,
      "entry_volume_ratio": 0.06070173123122017,
      "entry_score": 11.505358647266299,
      "current_price": 104.77999877929688,
      "current_pnl_pct": 0.0,
      "current_pnl_dollars": 0.0,
      "hold_days": 0,
      "status": "open",
      "exit_signal": null,
      "position_size": 5000,
      "in_top20": true
    },
    {
      "id": "ESI_2026-05-20",
      "ticker": "ESI",
      "sector": "Specialty Chemicals",
      "entry_date": "2026-05-20",
      "entry_price": 41.11000061035156,
      "entry_rsi2": 2.385125972056443,
      "entry_rsi30": 55.985294131456726,
      "entry_rs_vs_spy": 4.065848517209969,
      "entry_volume_ratio": 0.08930807111259494,
      "entry_score": 14.742136928660058,
      "current_price": 41.11000061035156,
      "current_pnl_pct": 0.0,
      "current_pnl_dollars": 0.0,
      "hold_days": 0,
      "status": "open",
      "exit_signal": null,
      "position_size": 5000,
      "in_top20": true
    },
    {
      "id": "PLXS_2026-05-20",
      "ticker": "PLXS",
      "sector": "Electronic Manufacturing Services",
      "entry_date": "2026-05-20",
      "entry_price": 258.3800048828125,
      "entry_rsi2": 3.6638780179545876,
      "entry_rsi30": 60.754200167501175,
      "entry_rs_vs_spy": 2.3917506167064007,
      "entry_volume_ratio": 0.07258200026637221,
      "entry_score": 10.426904582129087,
      "current_price": 258.3800048828125,
      "current_pnl_pct": 0.0,
      "current_pnl_dollars": 0.0,
      "hold_days": 0,
      "status": "open",
      "exit_signal": null,
      "position_size": 5000,
      "in_top20": true
    }
  ],
  "positions_all": [
    {
      "id": "FIX_2026-05-20",
      "ticker": "FIX",
      "sector": "Industrials",
      "entry_date": "2026-05-20",
      "entry_price": 1872.5,
      "entry_rsi2": 3.1767659900552445,
      "entry_rsi30": 58.868260152653136,
      "entry_rs_vs_spy": 5.3394314786773265,
      "entry_volume_ratio": 0.06473959692697623,
      "entry_score": 14.309597483201719,
      "current_price": 1849.7850341796875,
      "current_pnl_pct": -1.213082286799061,
      "current_pnl_dollars": -60.65411433995305,
      "hold_days": 0,
      "status": "open",
      "exit_signal": null,
      "position_size": 5000,
      "in_top20": true
    },
    {
      "id": "STX_2026-05-20",
      "ticker": "STX",
      "sector": "Information Technology",
      "entry_date": "2026-05-20",
      "entry_price": 753.0,
      "entry_rsi2": 3.77422034992,
      "entry_rsi30": 65.45743153503098,
      "entry_rs_vs_spy": 26.568503042343306,
      "entry_volume_ratio": 0.04254156990226344,
      "entry_score": 27.664267149671318,
      "current_price": 744.1699829101562,
      "current_pnl_pct": -1.17264503185176,
      "current_pnl_dollars": -58.632251592588005,
      "hold_days": 0,
      "status": "open",
      "exit_signal": null,
      "position_size": 5000,
      "in_top20": true
    },
    {
      "id": "NVT_2026-05-20",
      "ticker": "NVT",
      "sector": "Electrical Components & Equipment",
      "entry_date": "2026-05-20",
      "entry_price": 160.1699981689453,
      "entry_rsi2": 4.38057920549052,
      "entry_rsi30": 60.33749404758043,
      "entry_rs_vs_spy": 11.183436666113211,
      "entry_volume_ratio": 0.02364356561214219,
      "entry_score": 17.54049608319288,
      "current_price": 160.86000061035156,
      "current_pnl_pct": 0.43079381238328995,
      "current_pnl_dollars": 21.539690619164496,
      "hold_days": 0,
      "status": "open",
      "exit_signal": null,
      "position_size": 5000,
      "in_top20": true
    },
    {
      "id": "VMI_2026-05-20",
      "ticker": "VMI",
      "sector": "Industrial Machinery & Supplies & Components",
      "entry_date": "2026-05-20",
      "entry_price": 494.1300048828125,
      "entry_rsi2": 2.3725370626759457,
      "entry_rsi30": 57.21750808605591,
      "entry_rs_vs_spy": 2.5801478766408037,
      "entry_volume_ratio": 0.02019283935488425,
      "entry_score": 12.936037948063333,
      "current_price": 497.3900146484375,
      "current_pnl_pct": 0.6597473809343279,
      "current_pnl_dollars": 32.987369046716395,
      "hold_days": 0,
      "status": "open",
      "exit_signal": null,
      "position_size": 5000,
      "in_top20": true
    },
    {
      "id": "ROG_2026-05-20",
      "ticker": "ROG",
      "sector": "Electronic Components",
      "entry_date": "2026-05-20",
      "entry_price": 131.3699951171875,
      "entry_rsi2": 4.584553971529488,
      "entry_rsi30": 57.075794528542026,
      "entry_rs_vs_spy": 5.536113939691333,
      "entry_volume_ratio": 0.017007323794128396,
      "entry_score": 11.452042615603,
      "current_price": 131.0,
      "current_pnl_pct": -0.28164354947067816,
      "current_pnl_dollars": -14.082177473533907,
      "hold_days": 0,
      "status": "open",
      "exit_signal": null,
      "position_size": 5000,
      "in_top20": true
    },
    {
      "id": "VECO_2026-05-20",
      "ticker": "VECO",
      "sector": "Semiconductor Materials & Equipment",
      "entry_date": "2026-05-20",
      "entry_price": 56.31999969482422,
      "entry_rsi2": 2.526389671611369,
      "entry_rsi30": 62.73940224539524,
      "entry_rs_vs_spy": 8.526640112809947,
      "entry_volume_ratio": 0.04136459924707302,
      "entry_score": 18.68068376582257,
      "current_price": 57.025001525878906,
      "current_pnl_pct": 1.2517788261271479,
      "current_pnl_dollars": 62.58894130635739,
      "hold_days": 0,
      "status": "open",
      "exit_signal": null,
      "position_size": 5000,
      "in_top20": true
    },
    {
      "id": "MCHP_2026-05-20",
      "ticker": "MCHP",
      "sector": "Information Technology",
      "entry_date": "2026-05-20",
      "entry_price": 93.63999938964844,
      "entry_rsi2": 2.207752640766145,
      "entry_rsi30": 61.09111629729192,
      "entry_rs_vs_spy": 9.837552070029698,
      "entry_volume_ratio": 0.08175834086652578,
      "entry_score": 20.830838492830036,
      "current_price": 93.63999938964844,
      "current_pnl_pct": 0.0,
      "current_pnl_dollars": 0.0,
      "hold_days": 0,
      "status": "open",
      "exit_signal": null,
      "position_size": 5000,
      "in_top20": true
    },
    {
      "id": "FLEX_2026-05-20",
      "ticker": "FLEX",
      "sector": "Electronic Manufacturing Services",
      "entry_date": "2026-05-20",
      "entry_price": 133.3300018310547,
      "entry_rsi2": 4.727103490863556,
      "entry_rsi30": 68.63992658788753,
      "entry_rs_vs_spy": 52.39457737333362,
      "entry_volume_ratio": 0.24015597985175982,
      "entry_score": 26.746572917531687,
      "current_price": 133.3300018310547,
      "current_pnl_pct": 0.0,
      "current_pnl_dollars": 0.0,
      "hold_days": 0,
      "status": "open",
      "exit_signal": null,
      "position_size": 5000,
      "in_top20": true
    },
    {
      "id": "MSM_2026-05-20",
      "ticker": "MSM",
      "sector": "Trading Companies & Distributors",
      "entry_date": "2026-05-20",
      "entry_price": 104.77999877929688,
      "entry_rsi2": 4.247260626263056,
      "entry_rsi30": 60.495020372311046,
      "entry_rs_vs_spy": 4.69637124363631,
      "entry_volume_ratio": 0.06070173123122017,
      "entry_score": 11.505358647266299,
      "current_price": 104.77999877929688,
      "current_pnl_pct": 0.0,
      "current_pnl_dollars": 0.0,
      "hold_days": 0,
      "status": "open",
      "exit_signal": null,
      "position_size": 5000,
      "in_top20": true
    },
    {
      "id": "ESI_2026-05-20",
      "ticker": "ESI",
      "sector": "Specialty Chemicals",
      "entry_date": "2026-05-20",
      "entry_price": 41.11000061035156,
      "entry_rsi2": 2.385125972056443,
      "entry_rsi30": 55.985294131456726,
      "entry_rs_vs_spy": 4.065848517209969,
      "entry_volume_ratio": 0.08930807111259494,
      "entry_score": 14.742136928660058,
      "current_price": 41.11000061035156,
      "current_pnl_pct": 0.0,
      "current_pnl_dollars": 0.0,
      "hold_days": 0,
      "status": "open",
      "exit_signal": null,
      "position_size": 5000,
      "in_top20": true
    },
    {
      "id": "PLXS_2026-05-20",
      "ticker": "PLXS",
      "sector": "Electronic Manufacturing Services",
      "entry_date": "2026-05-20",
      "entry_price": 258.3800048828125,
      "entry_rsi2": 3.6638780179545876,
      "entry_rsi30": 60.754200167501175,
      "entry_rs_vs_spy": 2.3917506167064007,
      "entry_volume_ratio": 0.07258200026637221,
      "entry_score": 10.426904582129087,
      "current_price": 258.3800048828125,
      "current_pnl_pct": 0.0,
      "current_pnl_dollars": 0.0,
      "hold_days": 0,
      "status": "open",
      "exit_signal": null,
      "position_size": 5000,
      "in_top20": true
    }
  ],
  "summary": {
    "top20": {
      "open_count": 11,
      "total_unrealized_pnl": -16.25,
      "total_capital_deployed": 55000
    },
    "all": {
      "open_count": 11,
      "total_unrealized_pnl": -16.25,
      "total_capital_deployed": 55000
    }
  },
  "last_updated": "2026-05-20T14:22:28.116029Z",
  "spy_price": 737.4749755859375,
  "spy_above_200sma": true,
  "strategy": "UltraQ_90_RS2",
  "strategy_config": {
    "rsi2_entry": 5,
    "rsi2_exit": 65,
    "rsi30_min": 55,
    "max_hold_days": 2,
    "rs_threshold": 2.0,
    "near_high_pct": 90
  }
}